{
  "center_code": "SACC",
  "center_name": "Sacramento",
  "incident_count": 19,
  "incidents": [
    {
      "id": "0613",
      "time": "3:09 PM",
      "type": "Trfc Collision-Unkn Inj",
      "location": "Watt Ave / Tembrook Dr",
      "location_desc": "",
      "area": "North Sac"
    },
    {
      "id": "0609",
      "time": "3:07 PM",
      "type": "Trfc Collision-1141 Enrt",
      "location": "Grass Valley Hwy / Dry Creek Rd",
      "location_desc": "NB 49 JSO DRY CREEK",
      "area": "Auburn"
    },
    {
      "id": "0608",
      "time": "3:04 PM",
      "type": "Report of Fire",
      "location": "Stockton Blvd / Mcmahon Dr",
      "location_desc": "",
      "area": "South Sac"
    },
    {
      "id": "0038",
      "time": "3:03 PM",
      "type": "Trfc Collision-Unkn Inj",
      "location": "Us50 E / Howe Ave",
      "location_desc": "EB 50 AT HOWE",
      "area": "South Sac FSP"
    },
    {
      "id": "0601",
      "time": "3:00 PM",
      "type": "Trfc Collision-No Inj",
      "location": "S Watt Ave / Jackson Rd",
      "location_desc": "SB JNO",
      "area": "East Sac"
    },
    {
      "id": "0037",
      "time": "3:00 PM",
      "type": "Traffic Hazard",
      "location": "Us50 E / 15th St Ofr",
      "location_desc": "",
      "area": "South Sac FSP"
    },
    {
      "id": "0597",
      "time": "3:00 PM",
      "type": "Traffic Hazard",
      "location": "Us50 W / Jwo 65th St",
      "location_desc": "JWO",
      "area": "South Sac"
    },
    {
      "id": "0036",
      "time": "2:57 PM",
      "type": "Traffic Hazard",
      "location": "Sr99 N / Jso Mack Rd",
      "location_desc": "NB 99 JSO MACK",
      "area": "South Sac FSP"
    },
    {
      "id": "0595",
      "time": "2:56 PM",
      "type": "Trfc Collision-Unkn Inj",
      "location": "Us50 E / Howe Ave",
      "location_desc": "EB 50 AT HOWE",
      "area": "South Sac"
    },
    {
      "id": "0585",
      "time": "2:49 PM",
      "type": "Traffic Hazard",
      "location": "Sr193 / Chili Bar Ct",
      "location_desc": "",
      "area": "Placerville"
    },
    {
      "id": "0568",
      "time": "2:29 PM",
      "type": "Hit and Run No Injuries",
      "location": "5545 Marconi Ave",
      "location_desc": "IN PLOT",
      "area": "North Sac"
    },
    {
      "id": "0552",
      "time": "2:16 PM",
      "type": "Trfc Collision-No Inj",
      "location": "Arden Way / Eastern Ave",
      "location_desc": "WHOLE FOODS",
      "area": "North Sac"
    },
    {
      "id": "0543",
      "time": "2:14 PM",
      "type": "Traffic Hazard",
      "location": "I5 S / Bypass",
      "location_desc": "SB 5 AT BYPASS MIDSPAN",
      "area": "Woodland"
    },
    {
      "id": "0523",
      "time": "2:08 PM",
      "type": "Trfc Collision-1141 Enrt",
      "location": "Cr23 / Cr87b",
      "location_desc": "BTWN CR 87B / CR 89",
      "area": "Woodland"
    },
    {
      "id": "0517",
      "time": "2:01 PM",
      "type": "Hit and Run No Injuries",
      "location": "Lincolnshire Dr / Florin Rd",
      "location_desc": "OCCURD WB FLORIN JEO FRANKLIN",
      "area": "South Sac"
    },
    {
      "id": "0479",
      "time": "1:39 PM",
      "type": "Trfc Collision-No Inj",
      "location": "Grass Valley Hwy / Lone Star Rd",
      "location_desc": "NB JNO",
      "area": "Auburn"
    },
    {
      "id": "0119",
      "time": "6:14 AM",
      "type": "Assist CT with Maintenance",
      "location": "11363 Mccourtney Rd",
      "location_desc": "*ROLLING MZP*",
      "area": "SA"
    },
    {
      "id": "0113",
      "time": "6:11 AM",
      "type": "Assist CT with Maintenance",
      "location": "Blairs Ln",
      "location_desc": "CALTRANS PLACERVILLE YARD",
      "area": ""
    },
    {
      "id": "0899",
      "time": "6:04 PM",
      "type": "Assist with Construction",
      "location": "Sr99 N / Florin Rd",
      "location_desc": "NB 99 AT FLORIN",
      "area": "South Sac"
    }
  ],
  "last_updated": "2025-09-23T18:12:40.037777"
}