{
  "center_code": "OCCC",
  "center_name": "Orange",
  "date": "2025-09-28",
  "total_incidents": 8,
  "incidents": [
    {
      "id": "0247",
      "time": "1:40 PM",
      "type": "Traffic Hazard",
      "location": "I5 S / Disney Way",
      "area": "SB 5 JNO DISNEY WAY",
      "details": "Westminster",
      "center_code": "OCCC",
      "is_new": true,
      "is_relevant": true,
      "lane_blockage": {
        "status": "no_blockage",
        "details": []
      }
    },
    {
      "id": "0244",
      "time": "1:27 PM",
      "type": "Trfc Collision-No Inj",
      "location": "I405 N / Fairview Rd Fv",
      "area": "NB 405 JSO FV",
      "details": "Santa Ana",
      "center_code": "OCCC",
      "is_new": true,
      "is_relevant": true,
      "lane_blockage": {
        "status": "no_blockage",
        "details": []
      }
    },
    {
      "id": "0234",
      "time": "12:59 PM",
      "type": "Trfc Collision-No Inj",
      "location": "Sr57 S / Yorba Linda Blvd Yl",
      "area": "SB 57 JNO YL",
      "details": "Santa Ana",
      "center_code": "OCCC",
      "is_new": true,
      "is_relevant": true,
      "lane_blockage": {
        "status": "no_blockage",
        "details": []
      }
    },
    {
      "id": "0228",
      "time": "12:52 PM",
      "type": "Traffic Hazard",
      "location": "Sr73 S To / Sr55 S Con",
      "area": "SB 73 TRANS TO SB 55",
      "details": "Santa Ana",
      "center_code": "OCCC",
      "is_new": true,
      "is_relevant": true,
      "lane_blockage": {
        "status": "no_blockage",
        "details": []
      }
    },
    {
      "id": "0101",
      "time": "7:30 AM",
      "type": "CLOSURE of a Road",
      "location": "Sr73 N To / Sr55 S Con",
      "area": "NB 73 TO SB 55",
      "details": "Santa Ana",
      "center_code": "OCCC",
      "is_new": true,
      "is_relevant": true,
      "lane_blockage": {
        "status": "no_blockage",
        "details": []
      }
    },
    {
      "id": "0004",
      "time": "12:05 AM",
      "type": "CLOSURE of a Road",
      "location": "6681 Marine Way",
      "area": "OCCC",
      "details": "OC",
      "center_code": "OCCC",
      "is_new": true,
      "is_relevant": true,
      "lane_blockage": {
        "status": "no_blockage",
        "details": []
      }
    },
    {
      "id": "0003",
      "time": "12:05 AM",
      "type": "Road/Weather Conditions",
      "location": "6681 Marine Way",
      "area": "OC MEDIA LOG",
      "details": "OC",
      "center_code": "OCCC",
      "is_new": true,
      "is_relevant": true,
      "lane_blockage": {
        "status": "no_blockage",
        "details": []
      }
    },
    {
      "id": "0262",
      "time": "1:57 PM",
      "type": "Animal Hazard",
      "location": "Lampson Ave / Sr39",
      "area": "",
      "details": "OC",
      "center_code": "OCCC",
      "is_new": true,
      "is_relevant": true,
      "lane_blockage": {
        "status": "no_blockage",
        "details": []
      }
    }
  ],
  "last_updated": "2025-09-28T16:58:32.083677"
}