{
  "center_code": "BCCC",
  "center_name": "Border",
  "timestamp": "2025-09-28T16:25:55.064293",
  "new_incidents": [
    {
      "id": "0544",
      "time": "1:19 PM",
      "type": "Traffic Break",
      "location": "Sr163 S / Washington So",
      "area": "",
      "details": "San Diego",
      "center_code": "BCCC",
      "is_new": true,
      "is_relevant": true,
      "lane_blockage": {
        "status": "no_blockage",
        "details": []
      }
    },
    {
      "id": "0529",
      "time": "1:09 PM",
      "type": "Traffic Hazard",
      "location": "I5 N / Old Town So",
      "area": "I5 N OLD TOWN SO",
      "details": "San Diego",
      "center_code": "BCCC",
      "is_new": true,
      "is_relevant": true,
      "lane_blockage": {
        "status": "no_blockage",
        "details": []
      }
    },
    {
      "id": "0528",
      "time": "1:07 PM",
      "type": "Traffic Hazard",
      "location": "I15 S / Carroll Canyon",
      "area": "",
      "details": "San Diego",
      "center_code": "BCCC",
      "is_new": true,
      "is_relevant": true,
      "lane_blockage": {
        "status": "no_blockage",
        "details": []
      }
    },
    {
      "id": "0518",
      "time": "1:07 PM",
      "type": "Trfc Collision-1141 Enrt",
      "location": "I215 S / Ethanac No",
      "area": "I215 S ETHANAC NO",
      "details": "Temecula",
      "center_code": "BCCC",
      "is_new": true,
      "is_relevant": true,
      "lane_blockage": {
        "status": "no_blockage",
        "details": []
      }
    },
    {
      "id": "0516",
      "time": "1:06 PM",
      "type": "Traffic Hazard",
      "location": "I5 N / Pacific Hwy So",
      "area": "",
      "details": "San Diego",
      "center_code": "BCCC",
      "is_new": true,
      "is_relevant": true,
      "lane_blockage": {
        "status": "no_blockage",
        "details": []
      }
    },
    {
      "id": "0515",
      "time": "1:06 PM",
      "type": "Trfc Collision-No Inj",
      "location": "I15 S / Carroll Canyon",
      "area": "I15 S CARROLL CANYON",
      "details": "San Diego",
      "center_code": "BCCC",
      "is_new": true,
      "is_relevant": true,
      "lane_blockage": {
        "status": "no_blockage",
        "details": []
      }
    },
    {
      "id": "0507",
      "time": "1:00 PM",
      "type": "Trfc Collision-Unkn Inj",
      "location": "I5 N / CANNON NO",
      "area": "",
      "details": "Oceanside",
      "center_code": "BCCC",
      "is_new": true,
      "is_relevant": true,
      "lane_blockage": {
        "status": "no_blockage",
        "details": []
      }
    },
    {
      "id": "0502",
      "time": "12:57 PM",
      "type": "Traffic Hazard",
      "location": "I5 S / Las Pulgas No",
      "area": "",
      "details": "Oceanside",
      "center_code": "BCCC",
      "is_new": true,
      "is_relevant": true,
      "lane_blockage": {
        "status": "no_blockage",
        "details": []
      }
    },
    {
      "id": "0040",
      "time": "12:48 PM",
      "type": "Trfc Collision-1141Enrt",
      "location": "I805 N / H St So",
      "area": "I805 N H ST SO",
      "details": "South FSP",
      "center_code": "BCCC",
      "is_new": true,
      "is_relevant": true,
      "lane_blockage": {
        "status": "no_blockage",
        "details": []
      }
    },
    {
      "id": "0486",
      "time": "12:47 PM",
      "type": "Trfc Collision-1141 Enrt",
      "location": "I805 N / H St So",
      "area": "",
      "details": "San Diego",
      "center_code": "BCCC",
      "is_new": true,
      "is_relevant": true,
      "lane_blockage": {
        "status": "no_blockage",
        "details": []
      }
    },
    {
      "id": "0480",
      "time": "12:41 PM",
      "type": "Traffic Hazard",
      "location": "Sr67 / Scripps Poway Pkwy",
      "area": "NB AT",
      "details": "El Cajon",
      "center_code": "BCCC",
      "is_new": true,
      "is_relevant": true,
      "lane_blockage": {
        "status": "no_blockage",
        "details": []
      }
    },
    {
      "id": "0471",
      "time": "12:34 PM",
      "type": "Trfc Collision-No Inj",
      "location": "Sr94 E / Spring Wo",
      "area": "",
      "details": "El Cajon",
      "center_code": "BCCC",
      "is_new": true,
      "is_relevant": true,
      "lane_blockage": {
        "status": "no_blockage",
        "details": []
      }
    },
    {
      "id": "0410",
      "time": "11:44 AM",
      "type": "Report of Fire",
      "location": "Sr79 / Sr78",
      "area": "SR79 SR78 (SANTA YSABEL - DUDLEYS)",
      "details": "El Cajon",
      "center_code": "BCCC",
      "is_new": true,
      "is_relevant": true,
      "lane_blockage": {
        "status": "no_blockage",
        "details": []
      }
    },
    {
      "id": "0380",
      "time": "11:23 AM",
      "type": "ESCORT for Road Conditions",
      "location": "Miramar",
      "area": "MCAS MIRAMAR",
      "details": "San Diego",
      "center_code": "BCCC",
      "is_new": true,
      "is_relevant": true,
      "lane_blockage": {
        "status": "no_blockage",
        "details": []
      }
    },
    {
      "id": "0270",
      "time": "10:44 AM",
      "type": "JUMPER",
      "location": "I805 N I8 W Con / I805 I8 W Con",
      "area": "NB 805 TRANS TO WB I8",
      "details": "San Diego",
      "center_code": "BCCC",
      "is_new": true,
      "is_relevant": true,
      "lane_blockage": {
        "status": "no_blockage",
        "details": []
      }
    },
    {
      "id": "0201",
      "time": "8:28 AM",
      "type": "Defective Traffic Signals",
      "location": "Sr67 N / Bradley Ave Ofr",
      "area": "",
      "details": "El Cajon",
      "center_code": "BCCC",
      "is_new": true,
      "is_relevant": true,
      "lane_blockage": {
        "status": "no_blockage",
        "details": []
      }
    },
    {
      "id": "0145",
      "time": "5:01 AM",
      "type": "Traffic Hazard",
      "location": "Olde Highway 80 / Marina Springs Ln",
      "area": "JEO",
      "details": "El Cajon",
      "center_code": "BCCC",
      "is_new": true,
      "is_relevant": true,
      "lane_blockage": {
        "status": "no_blockage",
        "details": []
      }
    },
    {
      "id": "0065",
      "time": "1:46 AM",
      "type": "Fatality",
      "location": "12776-13355 Sr76",
      "area": "WB",
      "details": "Oceanside",
      "center_code": "BCCC",
      "is_new": true,
      "is_relevant": true,
      "lane_blockage": {
        "status": "no_blockage",
        "details": []
      }
    },
    {
      "id": "0003",
      "time": "12:00 AM",
      "type": "Road/Weather Conditions",
      "location": "Media Log",
      "area": "NEWSWORTHY INCIDENTS",
      "details": "BC",
      "center_code": "BCCC",
      "is_new": true,
      "is_relevant": true,
      "lane_blockage": {
        "status": "no_blockage",
        "details": []
      }
    }
  ],
  "removed_incidents": [],
  "new_count": 19,
  "removed_count": 0
}